cimd/__init__.py
cimd/classes/__init__.py
cimd/classes/context.py
cimd/classes/metadata.py
cimd/classes/shields_link.py
cimd/cli.py
cimd/commands/__init__.py
cimd/commands/add.py
cimd/commands/delete.py
cimd/commands/extend/__init__.py
cimd/commands/extend/gitlab_link.py
cimd/commands/extract/__init__.py
cimd/commands/extract/coverage_xml.py
cimd/commands/extract/junit_xml.py
cimd/commands/extract/pipeline_logs.py
cimd/commands/extract/trivy_scans.py
cimd/commands/get.py
cimd/commands/list.py
cimd-0.11.1.dist-info/LICENSE
cimd-0.11.1.dist-info/METADATA
cimd-0.11.1.dist-info/WHEEL
cimd-0.11.1.dist-info/entry_points.txt
cimd-0.11.1.dist-info/RECORD
